pyodstibmivb/__init__.py
pyodstibmivb/odstibmivb.py
pyodstibmivb/routes.py
pyodstibmivb-0.9.3.dist-info/LICENSE.md
pyodstibmivb-0.9.3.dist-info/METADATA
pyodstibmivb-0.9.3.dist-info/WHEEL
pyodstibmivb-0.9.3.dist-info/top_level.txt
pyodstibmivb-0.9.3.dist-info/RECORD
