Metadata-Version: 2.1
Name: pyodstibmivb
Version: 0.9.3
Summary: A Python wrapper for the Stib-Mivb opendata API
Home-page: https://gitlab.com/EmilV2/pyodstibmivb
Author: Emil Vanherp
Author-email: emil@vanherp.me
License: MIT License
Platform: UNKNOWN
Classifier: Programming Language :: Python :: 3
Classifier: Programming Language :: Python :: 3.6
Classifier: Programming Language :: Python :: 3.7
Classifier: Programming Language :: Python :: 3.8
Classifier: License :: OSI Approved :: MIT License
Classifier: Operating System :: OS Independent
Requires-Python: >=3
License-File: LICENSE.md
Requires-Dist: aiohttp (>=3.5.4)
